compit_inext_api/__init__.py
compit_inext_api/api.py
compit_inext_api/connector.py
compit_inext_api/consts.py
compit_inext_api/device_definitions.py
compit_inext_api/params_dictionary.py
compit_inext_api/py.typed
compit_inext_api/definitions/__init__.py
compit_inext_api/definitions/devices_en.json
compit_inext_api/types/DeviceDefinitions.py
compit_inext_api/types/DeviceState.py
compit_inext_api/types/SystemInfo.py
compit_inext_api-0.7.0.dist-info/licenses/LICENSE
compit_inext_api-0.7.0.dist-info/METADATA
compit_inext_api-0.7.0.dist-info/WHEEL
compit_inext_api-0.7.0.dist-info/top_level.txt
compit_inext_api-0.7.0.dist-info/RECORD
