Metadata-Version: 2.4
Name: compit-inext-api
Version: 0.7.0
Summary: Compit Inext API - Python client
Author: Przemyslaw Grzywa
License: Apache-2.0
Project-URL: homepage, https://github.com/Przemko92/compit-inext-api
Project-URL: repository, https://github.com/Przemko92/compit-inext-api
Project-URL: issues, https://github.com/Przemko92/compit-inext-api/issues
Requires-Python: >=3.12
License-File: LICENSE
Requires-Dist: aiofiles
Requires-Dist: aiohttp
Dynamic: license-file
